{
  "id": "2ced03dc-d385-4dd6-b0d1-7e71be364825",
  "info": {
    "type": "Article",
    "authKey": "",
    "name": "Dossier API – getEntity",
    "status": "published",
    "valid": true,
    "validPublished": true
  },
  "fields": {
    "title": "Dossier API – getEntity",
    "slug": "dossier-api-get-entity",
    "description": "Learn how to use getEntity to get an entity with the Dossier API",
    "body": {
      "root": {
        "direction": "ltr",
        "format": "",
        "indent": 0,
        "type": "root",
        "version": 1,
        "children": [
          {
            "direction": "ltr",
            "format": "",
            "indent": 0,
            "type": "paragraph",
            "version": 1,
            "children": [
              {
                "detail": 0,
                "format": 16,
                "mode": "normal",
                "style": "",
                "text": "getEntity",
                "type": "text",
                "version": 1
              },
              {
                "detail": 0,
                "format": 0,
                "mode": "normal",
                "style": "",
                "text": " is used to get an entity. You can reference the entity by id or by a unique index reference. When referencing the entity by id, it's possible to fetch a specific version of the entity.",
                "type": "text",
                "version": 1
              }
            ]
          },
          {
            "direction": "ltr",
            "format": "",
            "indent": 0,
            "type": "code",
            "version": 1,
            "language": "typescript",
            "children": [
              {
                "detail": 0,
                "format": 0,
                "mode": "normal",
                "style": "",
                "text": "interface",
                "type": "code-highlight",
                "version": 1,
                "highlightType": "keyword"
              },
              {
                "detail": 0,
                "format": 0,
                "mode": "normal",
                "style": "",
                "text": " ",
                "type": "code-highlight",
                "version": 1
              },
              {
                "detail": 0,
                "format": 0,
                "mode": "normal",
                "style": "",
                "text": "DossierClient",
                "type": "code-highlight",
                "version": 1,
                "highlightType": "class-name"
              },
              {
                "detail": 0,
                "format": 0,
                "mode": "normal",
                "style": "",
                "text": " ",
                "type": "code-highlight",
                "version": 1
              },
              {
                "detail": 0,
                "format": 0,
                "mode": "normal",
                "style": "",
                "text": "{",
                "type": "code-highlight",
                "version": 1,
                "highlightType": "punctuation"
              },
              {
                "type": "linebreak",
                "version": 1
              },
              {
                "detail": 0,
                "format": 0,
                "mode": "normal",
                "style": "",
                "text": "  ",
                "type": "code-highlight",
                "version": 1
              },
              {
                "detail": 0,
                "format": 0,
                "mode": "normal",
                "style": "",
                "text": "getEntity",
                "type": "code-highlight",
                "version": 1,
                "highlightType": "function"
              },
              {
                "detail": 0,
                "format": 0,
                "mode": "normal",
                "style": "",
                "text": "(",
                "type": "code-highlight",
                "version": 1,
                "highlightType": "punctuation"
              },
              {
                "type": "linebreak",
                "version": 1
              },
              {
                "detail": 0,
                "format": 0,
                "mode": "normal",
                "style": "",
                "text": "    reference",
                "type": "code-highlight",
                "version": 1
              },
              {
                "detail": 0,
                "format": 0,
                "mode": "normal",
                "style": "",
                "text": ":",
                "type": "code-highlight",
                "version": 1,
                "highlightType": "operator"
              },
              {
                "detail": 0,
                "format": 0,
                "mode": "normal",
                "style": "",
                "text": " EntityReference ",
                "type": "code-highlight",
                "version": 1
              },
              {
                "detail": 0,
                "format": 0,
                "mode": "normal",
                "style": "",
                "text": "|",
                "type": "code-highlight",
                "version": 1,
                "highlightType": "operator"
              },
              {
                "detail": 0,
                "format": 0,
                "mode": "normal",
                "style": "",
                "text": " EntityVersionReference ",
                "type": "code-highlight",
                "version": 1
              },
              {
                "detail": 0,
                "format": 0,
                "mode": "normal",
                "style": "",
                "text": "|",
                "type": "code-highlight",
                "version": 1,
                "highlightType": "operator"
              },
              {
                "detail": 0,
                "format": 0,
                "mode": "normal",
                "style": "",
                "text": " UniqueIndexReference",
                "type": "code-highlight",
                "version": 1
              },
              {
                "detail": 0,
                "format": 0,
                "mode": "normal",
                "style": "",
                "text": ",",
                "type": "code-highlight",
                "version": 1,
                "highlightType": "punctuation"
              },
              {
                "type": "linebreak",
                "version": 1
              },
              {
                "detail": 0,
                "format": 0,
                "mode": "normal",
                "style": "",
                "text": "  ",
                "type": "code-highlight",
                "version": 1
              },
              {
                "detail": 0,
                "format": 0,
                "mode": "normal",
                "style": "",
                "text": ")",
                "type": "code-highlight",
                "version": 1,
                "highlightType": "punctuation"
              },
              {
                "detail": 0,
                "format": 0,
                "mode": "normal",
                "style": "",
                "text": ":",
                "type": "code-highlight",
                "version": 1,
                "highlightType": "operator"
              },
              {
                "detail": 0,
                "format": 0,
                "mode": "normal",
                "style": "",
                "text": " PromiseResult",
                "type": "code-highlight",
                "version": 1
              },
              {
                "detail": 0,
                "format": 0,
                "mode": "normal",
                "style": "",
                "text": "<",
                "type": "code-highlight",
                "version": 1,
                "highlightType": "operator"
              },
              {
                "type": "linebreak",
                "version": 1
              },
              {
                "detail": 0,
                "format": 0,
                "mode": "normal",
                "style": "",
                "text": "    Entity",
                "type": "code-highlight",
                "version": 1
              },
              {
                "detail": 0,
                "format": 0,
                "mode": "normal",
                "style": "",
                "text": ",",
                "type": "code-highlight",
                "version": 1,
                "highlightType": "punctuation"
              },
              {
                "type": "linebreak",
                "version": 1
              },
              {
                "detail": 0,
                "format": 0,
                "mode": "normal",
                "style": "",
                "text": "    ",
                "type": "code-highlight",
                "version": 1
              },
              {
                "detail": 0,
                "format": 0,
                "mode": "normal",
                "style": "",
                "text": "\"BadRequest\"",
                "type": "code-highlight",
                "version": 1,
                "highlightType": "string"
              },
              {
                "detail": 0,
                "format": 0,
                "mode": "normal",
                "style": "",
                "text": " ",
                "type": "code-highlight",
                "version": 1
              },
              {
                "detail": 0,
                "format": 0,
                "mode": "normal",
                "style": "",
                "text": "|",
                "type": "code-highlight",
                "version": 1,
                "highlightType": "operator"
              },
              {
                "detail": 0,
                "format": 0,
                "mode": "normal",
                "style": "",
                "text": " ",
                "type": "code-highlight",
                "version": 1
              },
              {
                "detail": 0,
                "format": 0,
                "mode": "normal",
                "style": "",
                "text": "\"NotFound\"",
                "type": "code-highlight",
                "version": 1,
                "highlightType": "string"
              },
              {
                "detail": 0,
                "format": 0,
                "mode": "normal",
                "style": "",
                "text": " ",
                "type": "code-highlight",
                "version": 1
              },
              {
                "detail": 0,
                "format": 0,
                "mode": "normal",
                "style": "",
                "text": "|",
                "type": "code-highlight",
                "version": 1,
                "highlightType": "operator"
              },
              {
                "detail": 0,
                "format": 0,
                "mode": "normal",
                "style": "",
                "text": " ",
                "type": "code-highlight",
                "version": 1
              },
              {
                "detail": 0,
                "format": 0,
                "mode": "normal",
                "style": "",
                "text": "\"NotAuthorized\"",
                "type": "code-highlight",
                "version": 1,
                "highlightType": "string"
              },
              {
                "detail": 0,
                "format": 0,
                "mode": "normal",
                "style": "",
                "text": " ",
                "type": "code-highlight",
                "version": 1
              },
              {
                "detail": 0,
                "format": 0,
                "mode": "normal",
                "style": "",
                "text": "|",
                "type": "code-highlight",
                "version": 1,
                "highlightType": "operator"
              },
              {
                "detail": 0,
                "format": 0,
                "mode": "normal",
                "style": "",
                "text": " ",
                "type": "code-highlight",
                "version": 1
              },
              {
                "detail": 0,
                "format": 0,
                "mode": "normal",
                "style": "",
                "text": "\"Generic\"",
                "type": "code-highlight",
                "version": 1,
                "highlightType": "string"
              },
              {
                "type": "linebreak",
                "version": 1
              },
              {
                "detail": 0,
                "format": 0,
                "mode": "normal",
                "style": "",
                "text": "  ",
                "type": "code-highlight",
                "version": 1
              },
              {
                "detail": 0,
                "format": 0,
                "mode": "normal",
                "style": "",
                "text": ">",
                "type": "code-highlight",
                "version": 1,
                "highlightType": "operator"
              },
              {
                "detail": 0,
                "format": 0,
                "mode": "normal",
                "style": "",
                "text": ";",
                "type": "code-highlight",
                "version": 1,
                "highlightType": "punctuation"
              },
              {
                "type": "linebreak",
                "version": 1
              },
              {
                "detail": 0,
                "format": 0,
                "mode": "normal",
                "style": "",
                "text": "}",
                "type": "code-highlight",
                "version": 1,
                "highlightType": "punctuation"
              },
              {
                "type": "linebreak",
                "version": 1
              },
              {
                "type": "linebreak",
                "version": 1
              },
              {
                "detail": 0,
                "format": 0,
                "mode": "normal",
                "style": "",
                "text": "interface",
                "type": "code-highlight",
                "version": 1,
                "highlightType": "keyword"
              },
              {
                "detail": 0,
                "format": 0,
                "mode": "normal",
                "style": "",
                "text": " ",
                "type": "code-highlight",
                "version": 1
              },
              {
                "detail": 0,
                "format": 0,
                "mode": "normal",
                "style": "",
                "text": "EntityReference",
                "type": "code-highlight",
                "version": 1,
                "highlightType": "class-name"
              },
              {
                "detail": 0,
                "format": 0,
                "mode": "normal",
                "style": "",
                "text": " ",
                "type": "code-highlight",
                "version": 1
              },
              {
                "detail": 0,
                "format": 0,
                "mode": "normal",
                "style": "",
                "text": "{",
                "type": "code-highlight",
                "version": 1,
                "highlightType": "punctuation"
              },
              {
                "type": "linebreak",
                "version": 1
              },
              {
                "detail": 0,
                "format": 0,
                "mode": "normal",
                "style": "",
                "text": "  id",
                "type": "code-highlight",
                "version": 1
              },
              {
                "detail": 0,
                "format": 0,
                "mode": "normal",
                "style": "",
                "text": ":",
                "type": "code-highlight",
                "version": 1,
                "highlightType": "operator"
              },
              {
                "detail": 0,
                "format": 0,
                "mode": "normal",
                "style": "",
                "text": " ",
                "type": "code-highlight",
                "version": 1
              },
              {
                "detail": 0,
                "format": 0,
                "mode": "normal",
                "style": "",
                "text": "string",
                "type": "code-highlight",
                "version": 1,
                "highlightType": "builtin"
              },
              {
                "detail": 0,
                "format": 0,
                "mode": "normal",
                "style": "",
                "text": ";",
                "type": "code-highlight",
                "version": 1,
                "highlightType": "punctuation"
              },
              {
                "type": "linebreak",
                "version": 1
              },
              {
                "detail": 0,
                "format": 0,
                "mode": "normal",
                "style": "",
                "text": "}",
                "type": "code-highlight",
                "version": 1,
                "highlightType": "punctuation"
              },
              {
                "type": "linebreak",
                "version": 1
              },
              {
                "type": "linebreak",
                "version": 1
              },
              {
                "detail": 0,
                "format": 0,
                "mode": "normal",
                "style": "",
                "text": "interface",
                "type": "code-highlight",
                "version": 1,
                "highlightType": "keyword"
              },
              {
                "detail": 0,
                "format": 0,
                "mode": "normal",
                "style": "",
                "text": " ",
                "type": "code-highlight",
                "version": 1
              },
              {
                "detail": 0,
                "format": 0,
                "mode": "normal",
                "style": "",
                "text": "EntityVersionReference",
                "type": "code-highlight",
                "version": 1,
                "highlightType": "class-name"
              },
              {
                "detail": 0,
                "format": 0,
                "mode": "normal",
                "style": "",
                "text": " ",
                "type": "code-highlight",
                "version": 1
              },
              {
                "detail": 0,
                "format": 0,
                "mode": "normal",
                "style": "",
                "text": "{",
                "type": "code-highlight",
                "version": 1,
                "highlightType": "punctuation"
              },
              {
                "type": "linebreak",
                "version": 1
              },
              {
                "detail": 0,
                "format": 0,
                "mode": "normal",
                "style": "",
                "text": "  id",
                "type": "code-highlight",
                "version": 1
              },
              {
                "detail": 0,
                "format": 0,
                "mode": "normal",
                "style": "",
                "text": ":",
                "type": "code-highlight",
                "version": 1,
                "highlightType": "operator"
              },
              {
                "detail": 0,
                "format": 0,
                "mode": "normal",
                "style": "",
                "text": " ",
                "type": "code-highlight",
                "version": 1
              },
              {
                "detail": 0,
                "format": 0,
                "mode": "normal",
                "style": "",
                "text": "string",
                "type": "code-highlight",
                "version": 1,
                "highlightType": "builtin"
              },
              {
                "detail": 0,
                "format": 0,
                "mode": "normal",
                "style": "",
                "text": ";",
                "type": "code-highlight",
                "version": 1,
                "highlightType": "punctuation"
              },
              {
                "type": "linebreak",
                "version": 1
              },
              {
                "detail": 0,
                "format": 0,
                "mode": "normal",
                "style": "",
                "text": "  version",
                "type": "code-highlight",
                "version": 1
              },
              {
                "detail": 0,
                "format": 0,
                "mode": "normal",
                "style": "",
                "text": ":",
                "type": "code-highlight",
                "version": 1,
                "highlightType": "operator"
              },
              {
                "detail": 0,
                "format": 0,
                "mode": "normal",
                "style": "",
                "text": " ",
                "type": "code-highlight",
                "version": 1
              },
              {
                "detail": 0,
                "format": 0,
                "mode": "normal",
                "style": "",
                "text": "number",
                "type": "code-highlight",
                "version": 1,
                "highlightType": "builtin"
              },
              {
                "detail": 0,
                "format": 0,
                "mode": "normal",
                "style": "",
                "text": ";",
                "type": "code-highlight",
                "version": 1,
                "highlightType": "punctuation"
              },
              {
                "type": "linebreak",
                "version": 1
              },
              {
                "detail": 0,
                "format": 0,
                "mode": "normal",
                "style": "",
                "text": "}",
                "type": "code-highlight",
                "version": 1,
                "highlightType": "punctuation"
              },
              {
                "type": "linebreak",
                "version": 1
              },
              {
                "type": "linebreak",
                "version": 1
              },
              {
                "detail": 0,
                "format": 0,
                "mode": "normal",
                "style": "",
                "text": "interface",
                "type": "code-highlight",
                "version": 1,
                "highlightType": "keyword"
              },
              {
                "detail": 0,
                "format": 0,
                "mode": "normal",
                "style": "",
                "text": " ",
                "type": "code-highlight",
                "version": 1
              },
              {
                "detail": 0,
                "format": 0,
                "mode": "normal",
                "style": "",
                "text": "UniqueIndexReference",
                "type": "code-highlight",
                "version": 1,
                "highlightType": "class-name"
              },
              {
                "detail": 0,
                "format": 0,
                "mode": "normal",
                "style": "",
                "text": " ",
                "type": "code-highlight",
                "version": 1
              },
              {
                "detail": 0,
                "format": 0,
                "mode": "normal",
                "style": "",
                "text": "{",
                "type": "code-highlight",
                "version": 1,
                "highlightType": "punctuation"
              },
              {
                "type": "linebreak",
                "version": 1
              },
              {
                "detail": 0,
                "format": 0,
                "mode": "normal",
                "style": "",
                "text": "  index",
                "type": "code-highlight",
                "version": 1
              },
              {
                "detail": 0,
                "format": 0,
                "mode": "normal",
                "style": "",
                "text": ":",
                "type": "code-highlight",
                "version": 1,
                "highlightType": "operator"
              },
              {
                "detail": 0,
                "format": 0,
                "mode": "normal",
                "style": "",
                "text": " ",
                "type": "code-highlight",
                "version": 1
              },
              {
                "detail": 0,
                "format": 0,
                "mode": "normal",
                "style": "",
                "text": "string",
                "type": "code-highlight",
                "version": 1,
                "highlightType": "builtin"
              },
              {
                "detail": 0,
                "format": 0,
                "mode": "normal",
                "style": "",
                "text": ";",
                "type": "code-highlight",
                "version": 1,
                "highlightType": "punctuation"
              },
              {
                "type": "linebreak",
                "version": 1
              },
              {
                "detail": 0,
                "format": 0,
                "mode": "normal",
                "style": "",
                "text": "  value",
                "type": "code-highlight",
                "version": 1
              },
              {
                "detail": 0,
                "format": 0,
                "mode": "normal",
                "style": "",
                "text": ":",
                "type": "code-highlight",
                "version": 1,
                "highlightType": "operator"
              },
              {
                "detail": 0,
                "format": 0,
                "mode": "normal",
                "style": "",
                "text": " ",
                "type": "code-highlight",
                "version": 1
              },
              {
                "detail": 0,
                "format": 0,
                "mode": "normal",
                "style": "",
                "text": "string",
                "type": "code-highlight",
                "version": 1,
                "highlightType": "builtin"
              },
              {
                "detail": 0,
                "format": 0,
                "mode": "normal",
                "style": "",
                "text": ";",
                "type": "code-highlight",
                "version": 1,
                "highlightType": "punctuation"
              },
              {
                "type": "linebreak",
                "version": 1
              },
              {
                "detail": 0,
                "format": 0,
                "mode": "normal",
                "style": "",
                "text": "}",
                "type": "code-highlight",
                "version": 1,
                "highlightType": "punctuation"
              }
            ]
          },
          {
            "direction": null,
            "format": "",
            "indent": 0,
            "type": "paragraph",
            "version": 1,
            "children": []
          }
        ]
      }
    }
  }
}
