{
  "entityTypes": [
    {
      "name": "Article",
      "adminOnly": false,
      "authKeyPattern": "none",
      "fields": [
        {
          "name": "title",
          "type": "String",
          "list": false,
          "required": true,
          "adminOnly": false,
          "isName": true,
          "multiline": false,
          "matchPattern": null,
          "index": null
        },
        {
          "name": "slug",
          "type": "String",
          "list": false,
          "required": true,
          "adminOnly": false,
          "isName": false,
          "multiline": false,
          "matchPattern": "slug",
          "index": "articleSlug"
        },
        {
          "name": "body",
          "type": "RichText",
          "list": false,
          "required": true,
          "adminOnly": false,
          "richTextNodes": [
            "root",
            "paragraph",
            "text",
            "linebreak",
            "list",
            "listitem",
            "entityLink",
            "heading",
            "code",
            "code-highlight"
          ],
          "entityTypes": [],
          "linkEntityTypes": [
            "GlossaryTerm",
            "Article"
          ],
          "valueTypes": []
        }
      ]
    },
    {
      "name": "Chapter",
      "adminOnly": false,
      "authKeyPattern": "none",
      "fields": [
        {
          "name": "items",
          "type": "ValueItem",
          "list": true,
          "required": true,
          "adminOnly": false,
          "valueTypes": [
            "ArticleTocItem",
            "TocItem"
          ]
        }
      ]
    },
    {
      "name": "GlossaryTerm",
      "adminOnly": false,
      "authKeyPattern": "none",
      "fields": [
        {
          "name": "title",
          "type": "String",
          "list": false,
          "required": true,
          "adminOnly": false,
          "isName": true,
          "multiline": false,
          "matchPattern": null,
          "index": null
        },
        {
          "name": "slug",
          "type": "String",
          "list": false,
          "required": true,
          "adminOnly": false,
          "isName": false,
          "multiline": false,
          "matchPattern": "slug",
          "index": "glossarySlug"
        },
        {
          "name": "description",
          "type": "RichText",
          "list": false,
          "required": true,
          "adminOnly": false,
          "richTextNodes": [
            "root",
            "paragraph",
            "text",
            "linebreak",
            "entityLink"
          ],
          "entityTypes": [],
          "linkEntityTypes": [
            "GlossaryTerm"
          ],
          "valueTypes": []
        }
      ]
    }
  ],
  "valueTypes": [
    {
      "name": "ArticleTocItem",
      "adminOnly": false,
      "fields": [
        {
          "name": "title",
          "type": "String",
          "list": false,
          "required": true,
          "adminOnly": false,
          "isName": false,
          "multiline": false,
          "matchPattern": null,
          "index": null
        },
        {
          "name": "article",
          "type": "Entity",
          "list": false,
          "required": true,
          "adminOnly": false,
          "entityTypes": [
            "Article"
          ]
        }
      ]
    },
    {
      "name": "TocItem",
      "adminOnly": false,
      "fields": [
        {
          "name": "title",
          "type": "String",
          "list": false,
          "required": true,
          "adminOnly": false,
          "isName": false,
          "multiline": false,
          "matchPattern": null,
          "index": null
        },
        {
          "name": "items",
          "type": "ValueItem",
          "list": true,
          "required": true,
          "adminOnly": false,
          "valueTypes": [
            "ArticleTocItem",
            "TocItem"
          ]
        }
      ]
    }
  ],
  "patterns": [
    {
      "name": "none",
      "pattern": "^none$"
    },
    {
      "name": "slug",
      "pattern": "^[a-z0-9-]+$"
    }
  ],
  "indexes": [
    {
      "name": "articleSlug",
      "type": "unique"
    },
    {
      "name": "glossarySlug",
      "type": "unique"
    }
  ]
}
